arnoldpaperboy/__init__.py
arnoldpaperboy/logger/__init__.py
arnoldpaperboy/logger/client.py
arnoldpaperboy/logger/handlers.py
arnoldpaperboy/logger/helpers.py
arnoldpaperboy/monitoring/__init__.py
arnoldpaperboy/monitoring/custom_metrics.py
arnoldpaperboy/utils/__init__.py
arnoldpaperboy/utils/resource.py
tests/__init__.py
tests/test_helpers.py
tests/test_logging_handlers.py
arnoldpaperboy-0.1.13.dist-info/LICENSE.rst
arnoldpaperboy-0.1.13.dist-info/METADATA
arnoldpaperboy-0.1.13.dist-info/WHEEL
arnoldpaperboy-0.1.13.dist-info/top_level.txt
arnoldpaperboy-0.1.13.dist-info/RECORD
