Metadata-Version: 2.1
Name: arnoldpaperboy
Version: 0.1.13
Summary: Deliver to stackdriver
Home-page: https://gitlab.com/satelligence/arnoldpaperboy
Author: Satelligence
Author-email: schut@satelligence.com
License: Apache-2.0
Requires-Python: >=3.5
License-File: LICENSE.rst
Requires-Dist: dealer<3.0.0,>=2.0.0
Requires-Dist: google-api-core<3.0.0,>=2.0.0
Requires-Dist: google-auth<3.0.0,>=2.0.0
Requires-Dist: google-auth-oauthlib<2.0.0,>=1.0.0
Requires-Dist: google-cloud-core<3.0.0,>=2.0.0
Requires-Dist: google-cloud-logging<4.0.0,>=3.0.0
Requires-Dist: google-cloud-monitoring<3.0.0,>=2.0.0
Requires-Dist: googleapis-common-protos<2.0.0,>=1.50.0
Requires-Dist: grpc-google-iam-v1<1.0.0,>=0.12.0
Requires-Dist: grpcio<2.0.0,>=1.30.0
Requires-Dist: six<2.0.0,>=1.0.0
